MANIFEST.in
README.txt
setup.py
lfs_criterion_us_states/__init__.py
lfs_criterion_us_states/models.py
lfs_criterion_us_states.egg-info/PKG-INFO
lfs_criterion_us_states.egg-info/SOURCES.txt
lfs_criterion_us_states.egg-info/dependency_links.txt
lfs_criterion_us_states.egg-info/not-zip-safe
lfs_criterion_us_states.egg-info/requires.txt
lfs_criterion_us_states.egg-info/top_level.txt