Metadata-Version: 1.1
Name: lfs-criterion-us-states
Version: 1.0
Summary: A criterion for LFS which provides a selection of US states.
Home-page: http://www.getlfs.com
Author: Kai Diefenbach
Author-email: kai.diefenbach@iqpp.de
License: BSD
Keywords: django e-commerce online-shop
Platform: UNKNOWN
Classifier: Environment :: Web Environment
Classifier: Framework :: Django
Classifier: License :: OSI Approved :: BSD License
Classifier: Operating System :: OS Independent
Classifier: Programming Language :: Python
